nonebot_plugin_marshoai-1.2.dist-info/METADATA
nonebot_plugin_marshoai-1.2.dist-info/WHEEL
nonebot_plugin_marshoai-1.2.dist-info/entry_points.txt
nonebot_plugin_marshoai-1.2.dist-info/licenses/LICENSE-LSO
nonebot_plugin_marshoai-1.2.dist-info/licenses/LICENSE-MIT
nonebot_plugin_marshoai-1.2.dist-info/licenses/LICENSE-MULAN
nonebot_plugin_marshoai/__init__.py
nonebot_plugin_marshoai/_types.py
nonebot_plugin_marshoai/cache/decos.py
nonebot_plugin_marshoai/config.py
nonebot_plugin_marshoai/constants.py
nonebot_plugin_marshoai/deal_latex.py
nonebot_plugin_marshoai/dev.py
nonebot_plugin_marshoai/extensions/mcp_extension/__init__.py
nonebot_plugin_marshoai/extensions/mcp_extension/client.py
nonebot_plugin_marshoai/extensions/mcp_extension/config.py
nonebot_plugin_marshoai/extensions/mcp_extension/server.py
nonebot_plugin_marshoai/handler.py
nonebot_plugin_marshoai/hooks.py
nonebot_plugin_marshoai/instances.py
nonebot_plugin_marshoai/marsho.py
nonebot_plugin_marshoai/marsho_onebot.py
nonebot_plugin_marshoai/metadata.py
nonebot_plugin_marshoai/models.py
nonebot_plugin_marshoai/observer.py
nonebot_plugin_marshoai/plugin/__init__.py
nonebot_plugin_marshoai/plugin/func_call/__init__.py
nonebot_plugin_marshoai/plugin/func_call/caller.py
nonebot_plugin_marshoai/plugin/func_call/models.py
nonebot_plugin_marshoai/plugin/func_call/params.py
nonebot_plugin_marshoai/plugin/func_call/utils.py
nonebot_plugin_marshoai/plugin/load.py
nonebot_plugin_marshoai/plugin/models.py
nonebot_plugin_marshoai/plugin/typing.py
nonebot_plugin_marshoai/plugin/utils.py
nonebot_plugin_marshoai/plugins/builtin_tools/__init__.py
nonebot_plugin_marshoai/plugins/builtin_tools/chat.py
nonebot_plugin_marshoai/plugins/builtin_tools/file_io.py
nonebot_plugin_marshoai/plugins/builtin_tools/liteyuki.py
nonebot_plugin_marshoai/plugins/builtin_tools/manager.py
nonebot_plugin_marshoai/plugins/builtin_tools/network.py
nonebot_plugin_marshoai/plugins/builtin_tools/utils.py
nonebot_plugin_marshoai/plugins/marshoai_bangumi/__init__.py
nonebot_plugin_marshoai/plugins/marshoai_bangumi/tools.json
nonebot_plugin_marshoai/plugins/twisuki_megakits/__init__.py
nonebot_plugin_marshoai/plugins/twisuki_megakits/mk_morse_code.py
nonebot_plugin_marshoai/plugins/twisuki_megakits/mk_nya_code.py
nonebot_plugin_marshoai/plugins/twisuki_petcat/__init__.py
nonebot_plugin_marshoai-1.2.dist-info/RECORD
