Metadata-Version: 2.1
Name: nonebot-plugin-marshoai
Version: 1.2
Summary: Nonebot2插件，调用Azure OpenAI等AI服务实现猫娘聊天
Author-Email: Asankilp <asankilp@outlook.com>, LiteyukiStudio <support@liteyuki.icu>
License: MIT, Mulan PSL v2
Project-URL: Homepage, https://marsho.liteyuki.org/
Requires-Python: <4.0,>=3.10
Requires-Dist: nonebot2>=2.4.0
Requires-Dist: nonebot-plugin-alconna>=0.57.1
Requires-Dist: nonebot-plugin-localstore>=0.7.1
Requires-Dist: zhDatetime>=2.0.0
Requires-Dist: aiohttp>=3.9
Requires-Dist: httpx>=0.27.0
Requires-Dist: ruamel.yaml>=0.18.6
Requires-Dist: pyyaml>=6.0.2
Requires-Dist: psutil>=6.1.0
Requires-Dist: beautifulsoup4>=4.12.3
Requires-Dist: pydantic>=2.10.3
Requires-Dist: litedoc>=0.1.0.dev20241214103915
Requires-Dist: newspaper3k>=0.2.8
Requires-Dist: lxml[html_clean]>=5.3.0
Requires-Dist: aiofiles>=24.1.0
Requires-Dist: sumy>=0.11.0
Requires-Dist: azure-ai-inference>=1.0.0b6
Requires-Dist: watchdog>=6.0.0
Requires-Dist: nonebot-plugin-apscheduler>=0.5.0
Requires-Dist: openai>=1.58.1
Requires-Dist: nonebot-plugin-argot>=0.1.7
Requires-Dist: mcp[cli]>=1.9.0
